nuka/__init__.py
nuka/cli.py
nuka/configuration.py
nuka/gpg.py
nuka/log.py
nuka/process.py
nuka/reports.py
nuka/task.py
nuka/utils.py
nuka/hosts/__init__.py
nuka/hosts/base.py
nuka/hosts/cloud.py
nuka/hosts/docker_host.py
nuka/hosts/vagrant.py
nuka/inventory/__init__.py
nuka/inventory/libraries.py
nuka/inventory/net.py
nuka/inventory/operating_system.py
nuka/inventory/python.py
nuka/remote/__init__.py
nuka/remote/script.py
nuka/remote/task.py
nuka/tasks/__init__.py
nuka/tasks/apache.py
nuka/tasks/apt.py
nuka/tasks/archive.py
nuka/tasks/file.py
nuka/tasks/git.py
nuka/tasks/http.py
nuka/tasks/mysql.py
nuka/tasks/postgresql.py
nuka/tasks/service.py
nuka/tasks/setup.py
nuka/tasks/shell.py
nuka/tasks/user.py
nuka/tasks/virtualenv.py
nuka/tasks/yum.py
nuka/templates/reports/gantt.html.j2
nuka/templates/reports/gantt.js.j2
nuka/templates/reports/stats.html.j2
nuka/templates/sphinx/task_module.j2
nuka/templates/wordpress/apache.conf.j2
nuka/templates/wordpress/wp-config.php.j2
nuka-0.3.dist-info/DESCRIPTION.rst
nuka-0.3.dist-info/METADATA
nuka-0.3.dist-info/RECORD
nuka-0.3.dist-info/WHEEL
nuka-0.3.dist-info/entry_points.txt
nuka-0.3.dist-info/metadata.json
nuka-0.3.dist-info/top_level.txt
pytest_nuka/__init__.py
tests/tasks/__init__.py
tests/tasks/test_apt.py
tests/tasks/test_file.py
tests/tasks/test_git.py
tests/tasks/test_gpg.py
tests/tasks/test_http.py
tests/tasks/test_service.py
tests/tasks/test_shell.py
tests/tasks/test_user.py
tests/tasks/test_virtualenv.py
tests/tasks/test_yum.py
