Metadata-Version: 2.0
Name: nuka
Version: 0.3
Summary: provisioning tool focused on performance.
Home-page: UNKNOWN
Author: Bearstech
Author-email: py@bearstech.com
License: GPLv3
Keywords: devops docker vagrant gce
Platform: UNKNOWN
Classifier: Intended Audience :: Developers
Classifier: Programming Language :: Python :: 3.5
Classifier: Development Status :: 2 - Pre-Alpha
Classifier: Environment :: Console
Classifier: License :: OSI Approved :: GNU General Public License v3 or later (GPLv3+)
Classifier: Operating System :: POSIX
Classifier: Topic :: System :: Systems Administration
Requires-Dist: pyaml
Requires-Dist: jinja2
Requires-Dist: uvloop
Requires-Dist: asyncssh
Provides-Extra: cloud
Requires-Dist: python-novaclient; extra == 'cloud'
Requires-Dist: apache-libcloud; extra == 'cloud'
Requires-Dist: PyCrypto; extra == 'cloud'
Provides-Extra: docker
Requires-Dist: docker-compose; extra == 'docker'
Provides-Extra: full
Requires-Dist: tox; extra == 'full'
Requires-Dist: ujson; extra == 'full'
Requires-Dist: docker-compose; extra == 'full'
Requires-Dist: python-novaclient; extra == 'full'
Requires-Dist: apache-libcloud; extra == 'full'
Requires-Dist: PyCrypto; extra == 'full'
Requires-Dist: pytest; extra == 'full'
Requires-Dist: pytest-asyncio; extra == 'full'
Requires-Dist: coverage; extra == 'full'
Provides-Extra: speedup
Requires-Dist: ujson; extra == 'speedup'
Provides-Extra: test
Requires-Dist: ujson; extra == 'test'
Requires-Dist: docker-compose; extra == 'test'
Requires-Dist: python-novaclient; extra == 'test'
Requires-Dist: apache-libcloud; extra == 'test'
Requires-Dist: PyCrypto; extra == 'test'
Requires-Dist: pytest; extra == 'test'
Requires-Dist: pytest-asyncio; extra == 'test'
Requires-Dist: coverage; extra == 'test'
